pythonGroupMsg/__init__.py
pythonGroupMsg/build.sh
pythonGroupMsg/lib.c
pythonGroupMsg/lib.cpython-37m-x86_64-linux-gnu.so
pythonGroupMsg/lib.py
pythonGroupMsg/nlib.py
pythonGroupMsg/setup.py
pythonGroupMsg/test.py
pythonGroupMsg/__pycache__/__init__.cpython-37.pyc
pythonGroupMsg/__pycache__/nlib.cpython-37.pyc
pythonGroupMsg-0.0.8.dist-info/METADATA
pythonGroupMsg-0.0.8.dist-info/WHEEL
pythonGroupMsg-0.0.8.dist-info/top_level.txt
pythonGroupMsg-0.0.8.dist-info/RECORD
