Metadata-Version: 2.1
Name: pythonGroupMsg
Version: 0.0.8
Summary: This is a packet that broadcasts redis multiple queues
Home-page: https://github.com/zhenruyan/pythonGroupMsg
Author: zhenruyan
Author-email: baiyangwangzhan@hotmail.com
License: WTFPL
Platform: linux
Classifier: Operating System :: OS Independent
Classifier: Intended Audience :: Developers
Classifier: Programming Language :: Python :: 3.7
Classifier: Topic :: Software Development :: Libraries
